{
    "pflist" : [
        {
            "enuri" : [
                {"id" : "enuri_1",  "label" : "project_summerce", "title" : "소개페이지(react_swipe)", "date" : "", "url" : "//dev-hwon.github.io/dhreact/", "img_url" : "", "link" : true},
                {"id" : "enuri_1",  "label" : "project_sf", "title" : "스마트파인더(sf)", "date" : "", "url" : "", "img_url" : ""}
            ],
            "fuz" : [
                {"id" : "fuz_1", "label" : "project_si", "title" : "한샘몰_관리자페이지", "summary" : "메인페이지", "date" : "2021-04-01", "url" : "//thehyun1.dothome.co.kr/fuz/main/index.html", "img_url" : "//drive.google.com/uc?export=view&id=1SytiNtyRTgTrGmxMsbNXdUN1zCJRC0F7", "link" : true},
                {"id" : "fuz_2", "label" : "project_si", "title" : "한샘몰_관리자페이지", "summary" : "서브페이지(검색결과화면)", "date" : "2021-04-01", "url" : "//thehyun1.dothome.co.kr/fuz/search_result/list.html", "img_url" : "//drive.google.com/uc?export=view&id=1Fb-rnvIFVpzZ3IeFwzYRPn3Fefa439Bm", "link" : true},
                {"id" : "fuz_3", "label" : "project_si", "title" : "한샘몰_관리자페이지", "summary" : "서브페이지(노리스트)", "date" : "2021-04-01", "url" : "//thehyun1.dothome.co.kr/fuz/search_result/nolist.html", "img_url" : "//drive.google.com/uc?export=view&id=15OMCJU0GN94M_o1LMVgCWS3uJWhDqLhn", "link" : true},
                {"id" : "fuz_4", "label" : "project_si", "title" : "한샘몰_관리자페이지", "summary" : "공통게시판/목록 (리스트)", "date" : "2021-04-01", "url" : "//thehyun1.dothome.co.kr/fuz/board/default/list.html", "img_url" : "//drive.google.com/uc?export=view&id=1f2Ix5LTM8ljVOONr7T4SXkynPQbPHMr7", "link" : true},
                {"id" : "fuz_5", "label" : "project_si", "title" : "한샘몰_관리자페이지", "summary" : "공통게시판/상세", "date" : "2021-04-01", "url" : "//thehyun1.dothome.co.kr/fuz/board/default/view.html", "img_url" : "//drive.google.com/uc?export=view&id=1tTAd7meZlTCZ8bUOjbBWh1QDWnkMQSlm", "link" : true},
                {"id" : "fuz_6", "label" : "project_si", "title" : "한샘몰_관리자페이지", "summary" : "공통게시판/글쓰기", "date" : "2021-04-01", "url" : "//thehyun1.dothome.co.kr/fuz/board/default/write.html", "img_url" : "//drive.google.com/uc?export=view&id=1bhvWEwlyYQNU7somUOplUEksDSOpZB0U", "link" : true},
                {"id" : "fuz_7", "label" : "project_si", "title" : "한샘몰_관리자페이지", "summary" : "공통게시판/글수정", "date" : "2021-04-01", "url" : "//thehyun1.dothome.co.kr/fuz/board/default/modify.html", "img_url" : "//drive.google.com/uc?export=view&id=1E5w_55Lgbg1e37_s3uI9Z0lEH7Ifwjxp", "link" : true},
                {"id" : "fuz_8", "label" : "project_si", "title" : "한샘몰_관리자페이지", "summary" : "공통게시판/썸네일1", "date" : "2021-04-01", "url" : "//thehyun1.dothome.co.kr/fuz/board/default/list_thumbnail_re.html", "img_url" : "//drive.google.com/uc?export=view&id=1CHrg5p3CkHcpBRPbRfjJ31Iy1Wv8ru1j", "link" : true},
                {"id" : "fuz_8", "label" : "project_si", "title" : "한샘몰_관리자페이지", "summary" : "공통게시판/썸네일2", "date" : "2021-04-01", "url" : "//thehyun1.dothome.co.kr/fuz/board/default/list_thumbnail_re.html", "img_url" : "//drive.google.com/uc?export=view&id=1uSe8zbpuOB7XXnzLLTkAJ5ID8Zxx2t5i", "link" : true},
                {"id" : "fuz_9", "label" : "project_si", "title" : "한샘몰_관리자페이지", "summary" : "레이어팝업/의견보내기 ", "date" : "2021-04-01", "url" : "//thehyun1.dothome.co.kr/fuz/board/default/view.html", "img_url" : "//drive.google.com/uc?export=1D7JqRmeKPvTGWwxtFOnBmsU9VZL3R4WH", "link" : true},
                {"id" : "fuz_10", "label" : "project_si", "title" : "한샘몰_관리자페이지", "summary" : "레이어팝업/파일업로드", "date" : "2021-04-01", "url" : "//thehyun1.dothome.co.kr/fuz/board/default/write.html", "img_url" : "//drive.google.com/uc?export=1NfYO2gfqCbOKGT53qqCjnfsd80OM5NWa", "link" : true},

                {"id" : "fuz_11", "label" : "project_si", "title" : "한샘몰_관리자페이지", "summary" : "디지털상담가이드/C2 화면", "date" : "2021-04-01", "url" : "search_result2/view.html", "img_url" : "//drive.google.com/uc?export=view&id=1jkXeEMTfsYrHOkuID0H7pmZ26jDHfsmo", "detailImg_url":"//drive.google.com/uc?export=view&id=1jkXeEMTfsYrHOkuID0H7pmZ26jDHfsmo", "link" : false},
                {"id" : "fuz_12", "label" : "project_si", "title" : "한샘몰_관리자페이지", "summary" : "디지털상담가이드/C3 화면", "date" : "2021-04-01", "url" : "search_result2/list.html", "img_url" : "//drive.google.com/uc?export=1fCLA65uzkgSMzKmqkvSur69QlAfoeJdi", "detailImg_url":"//drive.google.com/uc?export=1fCLA65uzkgSMzKmqkvSur69QlAfoeJdi", "link" : false},
                {"id" : "fuz_13", "label" : "project_si", "title" : "한샘몰_관리자페이지", "summary" : "마이룸/메인", "date" : "2021-04-01", "url" : "myroom/index.html", "img_url" : "//drive.google.com/uc?export=view&id=1sEabQrExHEZA3NNfJW2pXLKGVehC75cI", "detailImg_url":"//drive.google.com/uc?export=view&id=1sEabQrExHEZA3NNfJW2pXLKGVehC75cI", "link" : false},
                {"id" : "fuz_14", "label" : "project_si", "title" : "한샘몰_관리자페이지", "summary" : "마이룸/스케쥴관리(월별)", "date" : "2021-04-01", "url" : "myroom/schedule.html", "img_url" : "//drive.google.com/uc?export=view&id=170opsO3WXuVtCWMVAl6LkeuvYEDB29cn", "detailImg_url":"//drive.google.com/uc?export=view&id=170opsO3WXuVtCWMVAl6LkeuvYEDB29cn", "link" : false},
                {"id" : "fuz_14", "label" : "project_si", "title" : "한샘몰_관리자페이지", "summary" : "마이룸/스케쥴관리(일별)", "date" : "2021-04-01", "url" : "myroom/schedule.html", "img_url" : "//drive.google.com/uc?export=view&id=1LrjD6Pf7TXvRMUST21Z2h0eeAJbWheBS", "detailImg_url":"//drive.google.com/uc?export=view&id=1LrjD6Pf7TXvRMUST21Z2h0eeAJbWheBS", "link" : false},
                {"id" : "fuz_15", "label" : "project_si", "title" : "한샘몰_관리자페이지", "summary" : "마이룸/팝업 - 등록", "date" : "2021-04-01", "url" : "myroom/schedule.html", "img_url" : "//drive.google.com/uc?export=1TA4_W-pvKerFj6joDTIyBVJsKbua8l33", "detailImg_url":"//drive.google.com/uc?export=1TA4_W-pvKerFj6joDTIyBVJsKbua8l33", "link" : false},
                {"id" : "fuz_15", "label" : "project_si", "title" : "한샘몰_관리자페이지", "summary" : "마이룸/팝업 - 상세", "date" : "2021-04-01", "url" : "myroom/schedule.html", "img_url" : "//drive.google.com/uc?export=1I3Gm_pAUnTQJqJlHzJe3eDvo2j1331uH", "detailImg_url":"//drive.google.com/uc?export=1I3Gm_pAUnTQJqJlHzJe3eDvo2j1331uH", "link" : false},
                {"id" : "fuz_16", "label" : "project_si", "title" : "한샘몰_관리자페이지", "summary" : "마이룸/팝업 - 수정", "date" : "2021-04-01", "url" : "myroom/schedule.html", "img_url" : "//drive.google.com/uc?export=1jh9qEspKiToV4lEt_Cn1Dg8TSWDo9Hmk", "detailImg_url":"//drive.google.com/uc?export=1jh9qEspKiToV4lEt_Cn1Dg8TSWDo9Hmk", "link" : false},
                {"id" : "fuz_18", "label" : "project_si", "title" : "한샘몰_관리자페이지", "summary" : "공통게시판/용어사전", "date" : "2021-04-01", "url" : "dictionary/index.html", "img_url" : "//drive.google.com/uc?export=view&id=13Lt1pil3m-WVpL1dDHRvxoBeNx5kTF4X", "detailImg_url":"//drive.google.com/uc?export=view&id=13Lt1pil3m-WVpL1dDHRvxoBeNx5kTF4X", "link" : false},
                {"id" : "fuz_19", "label" : "project_si", "title" : "한샘몰_관리자페이지", "summary" : "디지털상담가이드/원격시나리오지식관리 - Q1", "date" : "2021-04-01", "url" : "remote/index.html", "img_url" : "//drive.google.com/uc?export=view&id=1tXI-F_xYh2_PPHLEHPeOcAb_BfjiUYvH", "detailImg_url":"//drive.google.com/uc?export=view&id=1tXI-F_xYh2_PPHLEHPeOcAb_BfjiUYvH", "link" : false},
                {"id" : "fuz_20", "label" : "project_si", "title" : "한샘몰_관리자페이지", "summary" : "디지털상담가이드/원격시나리오지식관리 - Q2", "date" : "2021-04-01", "url" : "remote/index.html", "img_url" : "//drive.google.com/uc?export=view&id=1Vtux3RFtzMPUsehbxH1L1yjvqMN44dj0", "detailImg_url":"//drive.google.com/uc?export=view&id=1Vtux3RFtzMPUsehbxH1L1yjvqMN44dj0", "link" : false},
                {"id" : "fuz_21", "label" : "project_si", "title" : "한샘몰_관리자페이지", "summary" : "통계/메인", "date" : "2021-04-01", "url" : "static/index.html", "img_url" : "//drive.google.com/uc?export=view&id=1rQLxXfOjp0pqYowLR6BjXhSmvcPQhaPK", "detailImg_url":"//drive.google.com/uc?export=view&id=1rQLxXfOjp0pqYowLR6BjXhSmvcPQhaPK", "link" : false},
                {"id" : "fuz_23", "label" : "project_si", "title" : "한샘몰_관리자페이지", "summary" : "통계/게시물 통계/시스템활동별", "date" : "2021-04-01", "url" : "static/static_post.html", "img_url" : "//drive.google.com/uc?export=view&id=1IKgbWZhCYXM84uVLIilw48zdOIW2eNdo", "detailImg_url":"//drive.google.com/uc?export=view&id=1IKgbWZhCYXM84uVLIilw48zdOIW2eNdo", "link" : false},
                {"id" : "fuz_23", "label" : "project_si", "title" : "한샘몰_관리자페이지", "summary" : "통계/게시물 통계/게시물현황/분류체계별", "date" : "2021-04-01", "url" : "static/static_post.html", "img_url" : "//drive.google.com/uc?export=view&id=16emV3ETaIQcfK5MvIAkxZWYAvuAIfbof", "detailImg_url":"//drive.google.com/uc?export=view&id=16emV3ETaIQcfK5MvIAkxZWYAvuAIfbof", "link" : false},
                {"id" : "fuz_24", "label" : "project_si", "title" : "한샘몰_관리자페이지", "summary" : "통계/게시물 통계/게시물현황/메뉴별", "date" : "2021-04-01", "url" : "static/static_post.html", "img_url" : "//drive.google.com/uc?export=1NeU1gzDtrTZ9HduxHSzs4TfosIcaa7n-", "detailImg_url":"//drive.google.com/uc?export=1NeU1gzDtrTZ9HduxHSzs4TfosIcaa7n-", "link" : false},
                {"id" : "fuz_25", "label" : "project_si", "title" : "한샘몰_관리자페이지", "summary" : "통계/게시물 통계/리스트", "date" : "2021-04-01", "url" : "static/static_post_detail.html", "img_url" : "//drive.google.com/uc?export=view&id=1HMWkZcv-XjxENkhjTu2R-XJyJ-4vV9Ei", "detailImg_url":"//drive.google.com/uc?export=view&id=1HMWkZcv-XjxENkhjTu2R-XJyJ-4vV9Ei", "link" : false}
            ],
            "off" : [
                {"id" :"off_1", "label" : "Project_bid1", "title" : "재팬비드", "summary" : "일본옥션,일본구매대행,일본경매대행,메루카리구매대행,아마존 구매 및 일본쇼핑몰구매대행 배송대행", "date" : "2017-05-05" , "url" : "https://www.japanbid.co.kr", "img_url" : "/imgs/pf_thumbs/off/bid1.jpg", "link" : true},
                {"id" :"off_2", "label" : "Project_bid2", "title" : "도쿄비드", "summary" : "일본옥션, 일본구매, 라쿠텐, 야후재팬, 메루카리, 일본경매, 실시간입찰", "date" : "2017-05-06" , "url" : "https://www.tokyobid.kr", "img_url" : "/imgs/pf_thumbs/off/bid2.jpg", "link" : true},
                {"id" :"off_3", "label" : "Project_bid3", "title" : "위드바이몰", "summary" : "일본옥션,일본구매대행,일본경매대행,아마존 구매 및 일본쇼핑몰구매대행 배송대행", "date" : "2017-05-07" , "url" : "https://www.withbuymall.com", "img_url" : "/imgs/pf_thumbs/off/bid3.jpg", "link" : true},
                {"id" :"off_4", "label" : "Project_bid4", "title" : "클라우드비드", "summary" : "", "date" : "2017-05-08" , "url" : "https://www.cloudbid.co.kr", "img_url" : "/imgs/pf_thumbs/off/bid4.jpg", "link" : true},
                {"id" :"off_5", "label" : "Project_bid5", "title" : "비더스", "summary" : "", "date" : "2017-05-09" , "url" : "https://www.bidders.co.kr", "img_url" : "/imgs/pf_thumbs/off/bid5.jpg", "link" : true},
                {"id" :"off_6", "label" : "Project_bid6", "title" : "쇼핑월드", "summary" : "", "date" : "2017-05-10" , "url" : "https://www.shoppingworld.kr", "img_url" : "/imgs/pf_thumbs/off/bid6.jpg", "link" : true},
                
                {"id" :"off_7", "label" : "Project_cat1", "title" : "윈스몰", "summary" : "", "date" : "2019-05-11" , "url" : "https://www.winsmall.best", "img_url" : "/imgs/pf_thumbs/off/cat1.jpg", "link" : true},
                {"id" :"off_8", "label" : "Project_cat2", "title" : "포스트팀", "summary" : "", "date" : "2017-05-12" , "url" : "https://www.postteam.co.kr", "img_url" : "/imgs/pf_thumbs/off/cat2.jpg", "link" : true},
                {"id" :"off_9", "label" : "Project_cat3", "title" : "엘덱스", "summary" : "", "date" : "2017-05-13" , "url" : "https://www.eldex.co.kr", "img_url" : "/imgs/pf_thumbs/off/cat3.jpg", "link" : true},
                {"id" :"off_10", "label" : "Project_cat4", "title" : "지니커머스", "summary" : "", "date" : "2017-05-14" , "url" : "https://www.geniecommerce.co.kr", "img_url" : "/imgs/pf_thumbs/off/cat4.jpg", "link" : true},
                {"id" :"off_11", "label" : "Project_cat5", "title" : "포스트드림", "summary" : "", "date" : "2017-05-15" , "url" : "https://www.postdream.co.kr", "img_url" : "/imgs/pf_thumbs/off/cat5.jpg", "link" : true},
                {"id" :"off_12", "label" : "Project_cat6", "title" : "케이유", "summary" : "", "date" : "2019-05-16" , "url" : "https://www.k-you.co.kr", "img_url" : "/imgs/pf_thumbs/off/cat6.jpg", "link" : true},
                
                {"id" :"off_13", "label" : "Project_mall1", "title" : "줌마노리", "summary" : "", "date" : "2018-08-21" , "url" : "https://www.zummanori.com", "img_url" : "/imgs/pf_thumbs/off/mall1.jpg", "link" : true},
                {"id" :"off_14", "label" : "Project_mall2", "title" : "피규어방", "summary" : "", "date" : "2017-05-18" , "url" : "https://www.figurebang.co.kr", "img_url" : "/imgs/pf_thumbs/off/mall2.jpg", "link" : true},
                {"id" :"off_15", "label" : "Project_mall3", "title" : "재팬비드스토어", "summary" : "", "date" : "2017-05-19" , "url" : "https://www.japanbidstore.co.kr", "img_url" : "/imgs/pf_thumbs/off/mall3.jpg", "link" : true},
                {"id" :"off_16", "label" : "Project_mall4", "title" : "좋아요재팬", "summary" : "", "date" : "2017-05-20" , "url" : "https://www.joayojapan.com", "img_url" : "/imgs/pf_thumbs/off/mall4.jpg", "link" : true},
                {"id" :"off_17", "label" : "Project_mall5", "title" : "세이재팬", "summary" : "", "date" : "2017-05-21" , "url" : "https://www.sayjapan.co.kr", "img_url" : "/imgs/pf_thumbs/off/mall5.jpg", "link" : true},
                {"id" :"off_18", "label" : "Project_mall6", "title" : "재팬스토어", "summary" : "", "date" : "2017-05-22" , "url" : "https://www.japanstore.co.jp", "img_url" : "/imgs/pf_thumbs/off/mall6.jpg", "link" : true},
                
                {"id" :"off_19", "label" : "Project_re_cat1", "title" : "한마켓", "summary" : "", "date" : "2020-05-23" , "url" : "https://www.shop.hanpass.com", "img_url" : "/imgs/pf_thumbs/off/cat1.jpg", "link" : true},
                {"id" :"off_20", "label" : "Project_re_cat2", "title" : "케이맘", "summary" : "", "date" : "2019-01-14" , "url" : "https://www.k-mom.com", "img_url" : "/imgs/pf_thumbs/off/cat2.jpg", "link" : true},
                {"id" :"off_21", "label" : "Project_re_cat3", "title" : "케이맘샵", "summary" : "", "date" : "2019-02-12" , "url" : "https://www.shop.k-mom.com", "img_url" : "/imgs/pf_thumbs/off/cat3.jpg", "link" : true},
                {"id" :"off_22", "label" : "Project_re_cat4", "title" : "코박스", "summary" : "", "date" : "2019-11-01" , "url" : "https://www.ko-box.net", "img_url" : "/imgs/pf_thumbs/off/cat4.jpg", "link" : true},
                {"id" :"off_23", "label" : "Project_re_cat5", "title" : "에오에오", "summary" : "", "date" : "2017-05-27" , "url" : "https://www.eoeo.co.jp", "img_url" : "/imgs/pf_thumbs/off/cat5.jpg", "link" : true},
                {"id" :"off_24", "label" : "Project_re_cat6", "title" : "단짝", "summary" : "", "date" : "2017-05-28" , "url" : "https://www.danzzac.com", "img_url" : "/imgs/pf_thumbs/off/cat6.jpg", "link" : true}
            ],
            "vida" : [
                {"id" :"vida_1", "label" : "vida_na", "title" : "Native AD", "summary" : "국내 자율주행차 시대", "date" : "2014" , "url" : "", "img_url" : "//drive.google.com/uc?export=view&id=1oSkSPb7v-kY215mxQGxrgnDM-xiceJSX", "detailImg_url" : "//drive.google.com/uc?export=view&id=1j5l3vlyhKRiZmuIq8Lq4xqZnFViez4UL", "link" : false},
                {"id" :"vida_2", "label" : "vida_na", "title" : "Native AD", "summary" : "리니지 17주년", "date" : "2015" , "url" : "", "img_url" : "//drive.google.com/uc?export=view&id=15S2xzMaxyKwS_IHSxi5SucxsJaJ4KsUV", "detailImg_url" : "//drive.google.com/uc?export=view&id=11GxyQ2_4H-HO9VHmCf9QV47SIZirP7G8", "link" : false},
                {"id" :"vida_3", "label" : "vida_na", "title" : "Native AD", "summary" : "배트맨VS슈퍼맨", "date" : "2015" , "url" : "", "img_url" : "//drive.google.com/uc?export=view&id=1u7pGzWUsfh6sIUPXVX2bG78GTrmbzCQX", "detailImg_url" : "//drive.google.com/uc?export=view&id=1GQ09zxQTKw12NM8EYlD9M2xa2d4-k7px", "link" : false},
                {"id" :"vida_4", "label" : "vida_na", "title" : "Native AD", "summary" : "iPadPro VS  surfacePro4", "date" : "2015" , "url" : "", "img_url" : "//drive.google.com/uc?export=view&id=1iMA4peslzkGQAmGNElR4C8UuEPs8iKnh", "detailImg_url" : "//drive.google.com/uc?export=view&id=1j5UtvB05LWSpKhxoxJjYFgUWlvwkM_k6", "link" : false},
                
                {"id" :"vida_5", "label" : "vida_ds", "title" : "Digital Storytelling", "summary" : "청춘의민낯_강백수편", "date" : "2015" , "url" : "", "img_url" : "//drive.google.com/uc?export=view&id=1fRNOLzR9d-vqxi6edhqd3jADJcsuh9IW", "detailImg_url" : "//drive.google.com/uc?export=view&id=1Xz31IlxiYC2WpYweFuJRWXHJ0X61Qabd", "link" : false},
                {"id" :"vida_6", "label" : "vida_ds", "title" : "Digital Storytelling", "summary" : "당신의 두손가락은 몇그루의 나무를 심었나요", "date" : "2015" , "url" : "", "img_url" : "//drive.google.com/uc?export=view&id=1wuP24OrWHro-g0qVIck4-2f0Bs-FDK5t", "detailImg_url" : "//drive.google.com/uc?export=view&id=12rFdUy-yzWY4qSVxarcZ2WCrAn_kK3rv", "link" : false},
                {"id" :"vida_7", "label" : "vida_ds", "title" : "Digital Storytelling", "summary" : "우리 여전히 여기에 있어요", "date" : "2015" , "url" : "", "img_url" : "//drive.google.com/uc?export=view&id=1c_82KwXhWMvmnhLMeafcQdmtwBISLbni", "detailImg_url" : "//drive.google.com/uc?export=view&id=13NTHgTTeuqvbVy8Ae0ZlY-RVgZmQHQ0R", "link" : false},
                {"id" :"vida_8", "label" : "vida_ds", "title" : "Digital Storytelling", "summary" : "서른일곱의 삶, 그는 열정을 그렸다", "date" : "2015" , "url" : "",  "img_url" : "//drive.google.com/uc?export=view&id=1pNOpNdFNvYKy6ZZzPQlsMXjhaXRT__Aj", "detailImg_url" : "//drive.google.com/uc?export=view&id=1cXFvHrm7U8xYhOoE3X5iDt4dmxK0kmds", "link" : false},
                {"id" :"vida_9", "label" : "vida_ds", "title" : "Digital Storytelling", "summary" : "문정희가 살아가는 세상", "date" : "2015" , "url" : "", "img_url" : "//drive.google.com/uc?export=view&id=1h2G99z2nsB94yZy6419EjB4TgHvBpPJ7", "detailImg_url" : "//drive.google.com/uc?export=view&id=1pQJ5hsi6q1pI0r9K8LWpf07zdT0XthlE", "link" : false},
                {"id" :"vida_10", "label" : "vida_ds", "title" : "Digital Storytelling", "summary" : "응답하라 1990 감성발라드 오빠들이 돌아온다.", "date" : "2015" , "url" : "", "img_url" : "//drive.google.com/uc?export=view&id=1AC4w7SWXBU0JW7k2tiAvFv1h9Sdd0SMC", "detailImg_url" : "//drive.google.com/uc?export=view&id=1RWr1otkCnmooNUlqkKR91yERG7Gp80Zx", "link" : false},
                {"id" :"vida_11", "label" : "vida_ds", "title" : "Digital Storytelling", "summary" : "임성언에겐 '장미의전쟁'뿐이라고요?", "date" : "2015" , "url" : "", "img_url" : "//drive.google.com/uc?export=view&id=15CuTNBTr7oZsa0hR9fbco49uyMttM23k", "detailImg_url" : "//drive.google.com/uc?export=view&id=1lvGcP-ifJwuVmsh-MNQLdFb7w36OwGKr", "link" : false},
                {"id" :"vida_12", "label" : "vida_ds", "title" : "Digital Storytelling", "summary" : "디자인, '나'는 숨고 '너'를 돋보이게 하라", "date" : "2014" , "url" : "", "img_url" : "//drive.google.com/uc?export=view&id=17alwQn4uscOJc3SUh0jSAjFVcmQsTS6u", "detailImg_url" : "//drive.google.com/uc?export=view&id=1IVTjafSeaZhFRHyvEB5c3LfGurphb6aS", "link" : false},
                {"id" :"vida_13", "label" : "vida_ds", "title" : "Digital Storytelling", "summary" : "페북스타 세번째이야기_미녀스타강사 'JINA'", "date" : "2014" , "url" : "", "img_url" : "//drive.google.com/uc?export=view&id=1zIC1RBsm2sLkKJak-k10UKx3lPSITiS0", "detailImg_url" : "//drive.google.com/uc?export=view&id=13_061sLJhfcap5xZvc7dstoLJ97Q-3nz", "link" : false},
                {"id" :"vida_14", "label" : "vida_ds", "title" : "Digital Storytelling", "summary" : "다양성영화 상영관 생각보다 다양하다", "date" : "2014" , "url" : "", "img_url" : "//drive.google.com/uc?export=view&id=19OTZ_vyCUtu-F-bEEOVyAT5WHlkvFbjn", "detailImg_url" : "//drive.google.com/uc?export=view&id=1Gu-_ennlLpORyxZwJSiucNt6qi2qn2Rs", "link" : false},
                
                {"id" :"vida_15", "label" : "vida_vmag", "title" : "Visual magazin", "summary" : "오 나의 미친염소님", "date" : "2014" , "url" : "", "img_url" : "//drive.google.com/uc?export=view&id=1x0bPq8sxQiP25QAQwhZUzrBbR0eYMRgV", "detailImg_url" : "//drive.google.com/uc?export=view&id=1fK1s1yr2mWiuo89wEvj4mlc13z6C67rF", "link" : false},
                {"id" :"vida_16", "label" : "vida_vmag", "title" : "Visual magazin", "summary" : "Kiss Me Santa Claus", "date" : "2014" , "url" : "", "img_url" : "//drive.google.com/uc?export=view&id=1lDa6SzffO5ME6XaQrUF2zpBfuiRRWNID", "detailImg_url" : "//drive.google.com/uc?export=view&id=1lzIpA8rbzsrftl3MWVL0nccKPez3NqKa", "link" : false},
                {"id" :"vida_17", "label" : "vida_vmag", "title" : "Visual magazin", "summary" : "세 여행자가 청춘에게", "date" : "2014" , "url" : "", "img_url" : "//drive.google.com/uc?export=view&id=17dH2MDM3G-SbJDZwfwXIupPoEsm3FOFG", "detailImg_url" : "//drive.google.com/uc?export=view&id=1b3HmJ8zmm1iRuPFyBHaLnskeKU8bhdM6", "link" : false},
                {"id" :"vida_18", "label" : "vida_vmag", "title" : "Visual magazin", "summary" : "어디로 가야하죠, 아저씨. 우는 개미가 처음인가요.", "date" : "2014" , "url" : "", "img_url" : "//drive.google.com/uc?export=view&id=18kEiGqDuuxky_ti7Xg1rw15Ks1asDItd", "detailImg_url" : "//drive.google.com/uc?export=view&id=16frnJ1JDV7n22hNV_w38LF8sMigfC64U", "link" : false},
                {"id" :"vida_19", "label" : "vida_vmag", "title" : "Visual magazin", "summary" : "AMY WINEHOUSE", "date" : "2014" , "url" : "", "img_url" : "//drive.google.com/uc?export=view&id=1ANY4UAjhNsC75xvUIeREDDfjbwC9PeZ7", "detailImg_url" : "//drive.google.com/uc?export=view&id=1lqUDNTCYXUgqLe_i-zuy3RlKEpY6-854", "link" : false},
                {"id" :"vida_20", "label" : "vida_vmag", "title" : "Visual magazin", "summary" : "열정에 기름붓기", "date" : "2014" , "url" : "", "img_url" : "//drive.google.com/uc?export=view&id=1JI6xtuzmQdXAzTqaD51xEDFkajvNttM9", "detailImg_url" : "//drive.google.com/uc?export=view&id=1htsdblhawM2oePtbJDCZwS0LTMAV3z8O", "link" : false},
                {"id" :"vida_21", "label" : "vida_vmag", "title" : "Visual magazin", "summary" : "울지마, 음악으로 안아줄게", "date" : "2014" , "url" : "", "img_url" : "//drive.google.com/uc?export=view&id=1_Bohh0f50sP6kUUr2yLZZdL76bTluFYd", "detailImg_url" : "//drive.google.com/uc?export=view&id=1kihGgkoIImsfMiE30pk7_qggpXGdVz2r", "link" : false},
                {"id" :"vida_22", "label" : "vida_vmag", "title" : "Visual magazin", "summary" : "기차는 폐허로 떠나네", "date" : "2015" , "url" : "", "img_url" : "//drive.google.com/uc?export=view&id=1oCWPYTkQRRr65EzLEsrVjFNpFUb0IK0D", "detailImg_url" : "//drive.google.com/uc?export=view&id=1kIXw17tLwbmPztXove4TmL4_Hs8f2L5L", "link" : false},
                {"id" :"vida_23", "label" : "vida_vmag", "title" : "Visual magazin", "summary" : "YOU ARE MY MAP", "date" : "2015" , "url" : "", "img_url" : "//drive.google.com/uc?export=view&id=1oKZZ7ovTJ5SPNj6YqfoEuy8yCbEF5ArX", "detailImg_url" : "//drive.google.com/uc?export=view&id=1Ppx_laGqtksarZpbvdcb0ylMs72YYpCp", "link" : false},
                {"id" :"vida_24", "label" : "vida_vmag", "title" : "Visual magazin", "summary" : "자유로운 영혼의 울림, 패션이 되다", "date" : "2015" , "url" : "", "img_url" : "//drive.google.com/uc?export=view&id=13PNkFLjs6dvOZgF8pb32aT8QDlP3xuPt", "detailImg_url" : "//drive.google.com/uc?export=view&id=1RVqUXduM6eRfVdKHl8FGiluPAIF2jo6x", "link" : false},
                {"id" :"vida_25", "label" : "vida_vmag", "title" : "Visual magazin", "summary" : "거의 모든 패딩의 역사", "date" : "2015" , "url" : "", "img_url" : "//drive.google.com/uc?export=view&id=1apdHhEZwQzPSUS6nkNrI0a9eq-fQ9q3q", "detailImg_url" : "//drive.google.com/uc?export=view&id=1qaL4ORyPcD0wL9kOScafEze3PUXmsnfn", "link" : false},
                
                {"id" :"vida_26", "label" : "vida_vmag", "title" : "Visual magazin", "summary" : "20대 국회, 기대와 약속", "date" : "2015" , "url" : "", "img_url" : "//drive.google.com/uc?export=view&id=13qqB0aYGMS_aPzIhOfsfGNdIMogQqMsj", "detailImg_url" : "//drive.google.com/uc?export=view&id=1e8bJpMYJZT2Eu25TX9WYFxnXY5iMQJ5L", "link" : false}
            ]
        }
    ]
}
















